ghpr/__init__.py
ghpr/api.py
ghpr/cli.py
ghpr/comments.py
ghpr/config.py
ghpr/files.py
ghpr/gist.py
ghpr/patterns.py
ghpr/render.py
ghpr/commands/__init__.py
ghpr/commands/clone.py
ghpr/commands/create.py
ghpr/commands/diff.py
ghpr/commands/ingest_attachments.py
ghpr/commands/open.py
ghpr/commands/pull.py
ghpr/commands/push.py
ghpr/commands/shell_integration.py
ghpr/commands/show.py
ghpr/commands/upload.py
ghpr/shell/ghpr.bash
ghpr/shell/ghpr.fish
ghpr_py-0.1.4.dist-info/METADATA
ghpr_py-0.1.4.dist-info/WHEEL
ghpr_py-0.1.4.dist-info/entry_points.txt
ghpr_py-0.1.4.dist-info/top_level.txt
ghpr_py-0.1.4.dist-info/RECORD
