Metadata-Version: 2.4
Name: ghpr-py
Version: 0.1.4
Summary: GitHub PR/Issue management: clone, edit, and push PR/issue descriptions and comments, with gist mirroring
Author-email: Ryan Williams <ryan@runsascoded.com>
License: MIT
Project-URL: Repository, https://github.com/runsascoded/ghpr
Project-URL: Issues, https://github.com/runsascoded/ghpr/issues
Keywords: github,pr,issue,gist,cli
Classifier: Development Status :: 3 - Alpha
Classifier: Intended Audience :: Developers
Classifier: License :: OSI Approved :: MIT License
Classifier: Programming Language :: Python :: 3
Classifier: Programming Language :: Python :: 3.10
Classifier: Programming Language :: Python :: 3.11
Classifier: Programming Language :: Python :: 3.12
Classifier: Programming Language :: Python :: 3.13
Requires-Python: >=3.10
Requires-Dist: click>=8.0
Requires-Dist: utz>=0.21.3
Provides-Extra: test
Requires-Dist: pytest>=7.0; extra == "test"
